setup.py
flask_restful_jsonschema/__init__.py
flask_restful_jsonschema/flask_restful_jsonschema.py
flask_restful_jsonschema.egg-info/PKG-INFO
flask_restful_jsonschema.egg-info/SOURCES.txt
flask_restful_jsonschema.egg-info/dependency_links.txt
flask_restful_jsonschema.egg-info/top_level.txt