Metadata-Version: 1.0
Name: flask-restful-jsonschema
Version: 0.1.0
Summary: Provides a wrapper which provides valid json to Resource methods.
Home-page: UNKNOWN
Author: Lily Seabreeze
Author-email: lillian.gardenia.seabreeze@gmail.com
License: MIT
Platform: UNKNOWN
